nutsml/__init__.py
nutsml/batcher.py
nutsml/booster.py
nutsml/checkpoint.py
nutsml/common.py
nutsml/datautil.py
nutsml/fileutil.py
nutsml/imageutil.py
nutsml/logger.py
nutsml/metrics.py
nutsml/network.py
nutsml/plotter.py
nutsml/reader.py
nutsml/stratify.py
nutsml/transformer.py
nutsml/viewer.py
nutsml/writer.py
nutsml/examples/__init__.py
nutsml/examples/keras_/__init__.py
nutsml/examples/keras_/autoencoder/__init__.py
nutsml/examples/keras_/autoencoder/conv_autoencoder.py
nutsml/examples/keras_/autoencoder/runner.py
nutsml/examples/keras_/cifar/__init__.py
nutsml/examples/keras_/cifar/cnn_classify.py
nutsml/examples/keras_/cifar/cnn_train.py
nutsml/examples/keras_/cifar/read_images.py
nutsml/examples/keras_/cifar/view_augmented_images.py
nutsml/examples/keras_/cifar/view_data.py
nutsml/examples/keras_/cifar/view_train_images.py
nutsml/examples/keras_/cifar/write_images.py
nutsml/examples/keras_/mnist/__init__.py
nutsml/examples/keras_/mnist/cnn_classify.py
nutsml/examples/keras_/mnist/cnn_train.py
nutsml/examples/keras_/mnist/mlp_classify.py
nutsml/examples/keras_/mnist/mlp_train.py
nutsml/examples/keras_/mnist/mlp_view_misclassified.py
nutsml/examples/keras_/mnist/read_images.py
nutsml/examples/keras_/mnist/view_train_images.py
nutsml/examples/keras_/mnist/write_images.py
nutsml/examples/pytorch_/__init__.py
nutsml/examples/pytorch_/mnist/__init__.py
nutsml/examples/pytorch_/mnist/cnn_train.py
nutsml/examples/pytorch_/mnist/mlp_train.py
nutsml/examples/pytorch_/mnist/utils.py
tests/__init__.py
tests/data/and.csv
tests/data/and.txt
tests/data/iris.csv
tests/data/pandas_table.csv
tests/data/pandas_table.pkl
tests/data/pandas_table.tsv
tests/data/pandas_table.xlsx
tests/data/img/nut_color.bmp
tests/data/img/nut_grayscale.bmp
tests/data/img/plotlines.png
tests/data/img_arrays/nut_color.bmp.npy
tests/data/img_arrays/nut_color.gif.npy
tests/data/img_arrays/nut_color.jpg.npy
tests/data/img_arrays/nut_color.npy.npy
tests/data/img_arrays/nut_color.png.npy
nutsml-1.2.2.dist-info/LICENSE
nutsml-1.2.2.dist-info/METADATA
nutsml-1.2.2.dist-info/WHEEL
nutsml-1.2.2.dist-info/top_level.txt
nutsml-1.2.2.dist-info/RECORD
