Metadata-Version: 2.1
Name: nutsml
Version: 1.2.2
Summary: Flow-based data pre-processing for Machine Learning
Home-page: https://maet3608.github.io/nuts-ml
Author: Stefan Maetschke
Author-email: stefan.maetschke@gmail.com
License: Apache Software License (http://www.apache.org/licenses/LICENSE-2.0)
Download-URL: https://github.com/maet3608/nuts-ml
Keywords: machine learning,deep learning,image processing
Platform: any
Classifier: Development Status :: 5 - Production/Stable
Classifier: Programming Language :: Python :: 3.6
Classifier: Programming Language :: Python :: 3.7
Classifier: Programming Language :: Python :: 3.8
Classifier: Programming Language :: Python :: 3.9
Classifier: Natural Language :: English
Classifier: Intended Audience :: Developers
Classifier: Intended Audience :: Science/Research
Classifier: License :: OSI Approved :: Apache Software License
Classifier: Operating System :: OS Independent
Classifier: Topic :: Software Development :: Libraries :: Python Modules
Classifier: Topic :: Scientific/Engineering :: Artificial Intelligence
Requires-Dist: nutsflow (>=1.2.3)
Requires-Dist: openpyxl (>=3.0.5)
Requires-Dist: pandas (>0.21.0)
Requires-Dist: six (>=1.10.0)
Requires-Dist: scipy (>=0.17.0)
Requires-Dist: pillow (>=3.0.0)
Requires-Dist: scikit-image (>=0.12.3)
